urihandler/__init__.py
urihandler/handler.py
urihandler/utils.py
urihandler/views.py
urihandler-1.3.0.dist-info/METADATA
urihandler-1.3.0.dist-info/WHEEL
urihandler-1.3.0.dist-info/entry_points.txt
urihandler-1.3.0.dist-info/licenses/LICENSE
urihandler-1.3.0.dist-info/RECORD
