Metadata-Version: 2.1
Name: urihandler
Version: 1.3.0
Summary: A tiny application that handles (cool) uri's.
Project-URL: History, https://github.com/OnroerendErfgoed/urihandler/blob/master/CHANGES.rst
Project-URL: Tracker, https://github.com/OnroerendErfgoed/urihandler/issues
Project-URL: Source, https://github.com/OnroerendErfgoed/urihandler
Project-URL: Documentation, https://urihandler.readthedocs.io/en/latest/
Author-email: Flanders Heritage Agency <ict@onroerenderfgoed.be>
License-File: LICENSE
Keywords: SKOS,pyramid,thesaurus,vocabulary,web,wsgi
Classifier: Development Status :: 5 - Production/Stable
Classifier: Framework :: Pyramid
Classifier: Programming Language :: Python
Classifier: Programming Language :: Python :: 3.10
Classifier: Programming Language :: Python :: 3.11
Classifier: Programming Language :: Python :: 3.12
Classifier: Topic :: Internet :: WWW/HTTP
Classifier: Topic :: Internet :: WWW/HTTP :: WSGI :: Application
Requires-Python: <3.13,>=3.10
Requires-Dist: pyramid==2.0.2
Requires-Dist: pyyaml==6.0.1
Provides-Extra: dev
Requires-Dist: black==24.4.2; extra == 'dev'
Requires-Dist: coveralls==4.0.1; extra == 'dev'
Requires-Dist: flake8-import-order==0.18.2; extra == 'dev'
Requires-Dist: flake8==7.1.0; extra == 'dev'
Requires-Dist: pre-commit==3.7.1; extra == 'dev'
Requires-Dist: pyramid-debugtoolbar==4.12.1; extra == 'dev'
Requires-Dist: pytest-cov==5.0.0; extra == 'dev'
Requires-Dist: pytest==8.2.2; extra == 'dev'
Requires-Dist: waitress==3.0.0; extra == 'dev'
Requires-Dist: webtest==3.0.0; extra == 'dev'
